fcw_core/__init__.py
fcw_core/data/UbuntuMono-B.ttf
fcw_core/data/UbuntuMono-R.ttf
fcw_core/data/cog_logo.png
fcw_core/data/marker.png
fcw_core/detection.py
fcw_core/fcw_example.py
fcw_core/sort.py
fcw_core/vizualization.py
fcw_core/yolo_detector.py
fcw_core-0.12.1.dist-info/METADATA
fcw_core-0.12.1.dist-info/WHEEL
fcw_core-0.12.1.dist-info/entry_points.txt
fcw_core-0.12.1.dist-info/RECORD
