Metadata-Version: 2.1
Name: fcw-core
Version: 0.12.1
Summary: Early collision warning Network Application for Transportation use case - core part
Home-page: https://github.com/5G-ERA/CollisionWarningService
Author: Petr Kleparnik
Author-email: p.kleparnik@cognitechna.cz
Requires-Python: >=3.8
Classifier: Programming Language :: Python :: 3
Classifier: Programming Language :: Python :: 3.8
Classifier: Programming Language :: Python :: 3.9
Classifier: Programming Language :: Python :: 3.10
Classifier: Programming Language :: Python :: 3.11
Classifier: Programming Language :: Python :: 3.12
Requires-Dist: fcw-core-utils (>=0.12.1,<0.13.0)
Requires-Dist: filterpy (>=1.4.5)
Requires-Dist: gitpython (>=3.1.41)
Requires-Dist: matplotlib (>=3.7.4)
Requires-Dist: more-itertools (>=10.2.0)
Requires-Dist: opencv-python (>=4.8)
Requires-Dist: pandas (>=2.0.3)
Requires-Dist: psutil (>=5.9.8)
Requires-Dist: pyyaml (>=6.0)
Requires-Dist: requests (>=2.31.0)
Requires-Dist: seaborn (>=0.13.2)
Requires-Dist: setuptools (>=69.2.0)
Requires-Dist: shapely (>=2.0.2)
Requires-Dist: torch (>=2.1.0)
Requires-Dist: torchaudio (>=2.1.0)
Requires-Dist: torchvision (>=0.16.0)
Requires-Dist: tqdm (>=4.66.1)
Requires-Dist: ultralytics (>=8.1.19)
Requires-Dist: wheel (>=0.38.0)
Project-URL: Repository, https://github.com/5G-ERA/CollisionWarningService
